ZeusTheInvestigator/__init__.py
ZeusTheInvestigator/checker.py
zeustheinvestigator-0.1.7.dist-info/entry_points.txt
zeustheinvestigator-0.1.7.dist-info/WHEEL
zeustheinvestigator-0.1.7.dist-info/METADATA
zeustheinvestigator-0.1.7.dist-info/RECORD
