Metadata-Version: 2.1
Name: zeustheinvestigator
Version: 0.1.7
Summary: A pure python program that checks if a site is online at the moment
Home-page: https://github.com/777advait/Zeus-The-Investigator
License: MIT
Author: 777advait
Requires-Python: >=3.7,<4.0
Classifier: License :: OSI Approved :: MIT License
Classifier: Programming Language :: Python :: 3
Classifier: Programming Language :: Python :: 3.10
Classifier: Programming Language :: Python :: 3.7
Classifier: Programming Language :: Python :: 3.8
Classifier: Programming Language :: Python :: 3.9
Requires-Dist: requests (>=2.27.1,<3.0.0)
Requires-Dist: rich (>=12.4.3,<13.0.0)
Requires-Dist: typer (>=0.4.1,<0.5.0)
Requires-Dist: urllib3 (>=1.26.9,<2.0.0)
Project-URL: Bug Tracker, https://github.com/777advait/Zeus-The-Investigator/issues
Project-URL: Repository, https://github.com/777advait/Zeus-The-Investigator
